fudstop/__init__.py
fudstop/all_helpers.py
fudstop/options_filter.py
fudstop/plots.py
fudstop/schema.py
fudstop/_gpts/__init__.py
fudstop/_gpts/trader_ai.py
fudstop/_markets/__init__.py
fudstop/_markets/analyzers.py
fudstop/_markets/embeddings.py
fudstop/_markets/monitor - Copy.py
fudstop/_markets/monitor.py
fudstop/_markets/multimarkets.py
fudstop/_markets/stock_market.py
fudstop/_markets/webhook_dicts.py
fudstop/_markets/finished/__init__.py
fudstop/_markets/finished/db_manager.py
fudstop/_markets/finished/economic_data.py
fudstop/_markets/finished/master_class.py
fudstop/_markets/finished/td9_states.py
fudstop/_markets/list_sets/__init__.py
fudstop/_markets/list_sets/dicts.py
fudstop/_markets/list_sets/saved_tickers.py
fudstop/_markets/list_sets/ticker_lists.py
fudstop/_markets/list_sets/webhook_dicts.py
fudstop/_markets/market_handlers/__init__.py
fudstop/_markets/market_handlers/cfg.py
fudstop/_markets/market_handlers/crypto.py
fudstop/_markets/market_handlers/database_.py
fudstop/_markets/market_handlers/forex.py
fudstop/_markets/market_handlers/indices.py
fudstop/_markets/market_handlers/list_sets.py
fudstop/_markets/market_handlers/options.py
fudstop/_markets/market_handlers/stocks.py
fudstop/_markets/reference_markets/__init__.py
fudstop/_markets/reference_markets/conditional_scans.py
fudstop/_markets/reference_markets/reference_market.py
fudstop/_markets/scripts/__init__.py
fudstop/_markets/scripts/all_polygon_options.py
fudstop/_markets/scripts/all_webull_options.py
fudstop/_markets/scripts/generation.py
fudstop/_markets/scripts/million_dollar_trades.py
fudstop/_markets/scripts/option_scripts.py
fudstop/_markets/scripts/options_market.py
fudstop/_markets/scripts/options_volume_analysis.py
fudstop/_markets/scripts/rsi_2_4_8.py
fudstop/_markets/scripts/rsi_screener.py
fudstop/_markets/scripts/ssr_scanner.py
fudstop/_markets/scripts/stock_market.py
fudstop/_markets/scripts/td9_states.py
fudstop/_markets/scripts/universal_snapshot.py
fudstop/apis/__init__.py
fudstop2-8.3.6.dist-info/METADATA
fudstop2-8.3.6.dist-info/WHEEL
fudstop2-8.3.6.dist-info/top_level.txt
fudstop2-8.3.6.dist-info/RECORD
