Metadata-Version: 2.1
Name: fudstop2
Version: 8.3.6
Summary: A market data API aggregator for analysis and real-time feeds.
Home-page: https://github.com/your-username/fudstop2
Author: Chuck Dustin
Author-email: chuckdustin12@gmail.com
License: MIT
Classifier: Programming Language :: Python :: 3
Classifier: License :: OSI Approved :: MIT License
Classifier: Operating System :: OS Independent
Requires-Python: >=3.7
Requires-Dist: aiofiles==24.1.0
Requires-Dist: aiohttp==3.11.11
Requires-Dist: anyio==3.7.1
Requires-Dist: asyncpg==0.29.0
Requires-Dist: beautifulsoup4==4.13.3
Requires-Dist: certifi==2023.7.22
Requires-Dist: discord-webhook==1.3.1
Requires-Dist: disnake==2.10.1
Requires-Dist: faiss==1.5.3
Requires-Dist: feedparser==6.0.10
Requires-Dist: google-api-python-client==2.161.0
Requires-Dist: google-auth-oauthlib==1.1.0
Requires-Dist: gtts==2.5.4
Requires-Dist: httpcore==1.0.7
Requires-Dist: httpx==0.28.1
Requires-Dist: kaleido==0.2.1
Requires-Dist: langchain==0.3.19
Requires-Dist: lxml==4.9.3
Requires-Dist: matplotlib==3.10.0
Requires-Dist: more-itertools==10.6.0
Requires-Dist: moviepy==2.1.2
Requires-Dist: natsort==8.4.0
Requires-Dist: numpy==2.2.3
Requires-Dist: openai==1.63.2
Requires-Dist: orjson==3.10.15
Requires-Dist: pandas==2.2.3
Requires-Dist: pdf2image==1.17.0
Requires-Dist: Pillow==11.1.0
Requires-Dist: plotly==6.0.0
Requires-Dist: polygon==1.2.6
Requires-Dist: praw==7.8.1
Requires-Dist: protobuf==5.29.3
Requires-Dist: psycopg2==2.9.9
Requires-Dist: PyPDF2==3.0.1
Requires-Dist: python-dotenv==1.0.1
Requires-Dist: python-dateutil==2.8.2
Requires-Dist: pytrends==4.9.2
Requires-Dist: pytz==2023.3.post1
Requires-Dist: redis==5.2.1
Requires-Dist: Requests==2.32.3
Requires-Dist: scipy==1.15.2
Requires-Dist: seaborn==0.13.2
Requires-Dist: selenium==4.29.0
Requires-Dist: setuptools==75.1.0
Requires-Dist: stocksera==0.1.21
Requires-Dist: tabulate==0.9.0
Requires-Dist: tenacity==8.2.3
Requires-Dist: transformers==4.49.0
Requires-Dist: yfinance==0.2.54
